{
    "author": ["Kuro"],
    "description": "Restart/Shutdown your bot with reaction predicate!",
    "disabled": false,
    "end_user_data_statement": "This cog does not store any end user data.",
    "hidden": false,
    "install_msg": "Thanks for installing `ReactTermino`! Use `[p]help ReactTermino` to see all the available commands.\nThis cog has docs! Check it out at <https://kuro-cogs.readthedocs.io/en/latest/cogs/reacttermino.html>.",
    "name": "ReactTermino",
    "short": "Restart/Shutdown your bot with reaction predicate!",
    "tags": ["confirm", "confirmation", "predicate", "reaction", "restart", "shutdown"],
    "type": "COG"
}